ppw0810/__init__.py
ppw0810/app.py
ppw0810/cli.py
ppw0810-0.2.0.dist-info/entry_points.txt
ppw0810-0.2.0.dist-info/LICENSE
ppw0810-0.2.0.dist-info/WHEEL
ppw0810-0.2.0.dist-info/METADATA
ppw0810-0.2.0.dist-info/RECORD
